{
  "_fv": 73,
  "_type": "gui",
  "definition": {
    "type": 0,
    "width": 178,
    "height": 189,
    "inventoryOffsetX": 0,
    "inventoryOffsetY": 0,
    "renderBgLayer": true,
    "doesPauseGame": false,
    "components": [
      {
        "type": "image",
        "data": {
          "image": "experience_bottle.png",
          "use1Xscale": false,
          "x": 141,
          "y": 53,
          "locked": false
        }
      },
      {
        "type": "label",
        "data": {
          "name": "label_0_level",
          "text": {
            "fixedValue": "Level 1 (y)"
          },
          "color": {
            "value": -12829636,
            "falpha": 0.0
          },
          "x": 159,
          "y": 53,
          "locked": false
        }
      },
      {
        "type": "label",
        "data": {
          "name": "label_rage",
          "text": {
            "fixedValue": "Healing"
          },
          "color": {
            "value": -12829636,
            "falpha": 0.0
          },
          "x": 159,
          "y": 62,
          "locked": false
        }
      },
      {
        "type": "image",
        "data": {
          "image": "experience_bottle.png",
          "use1Xscale": false,
          "x": 141,
          "y": 80,
          "locked": false
        }
      },
      {
        "type": "label",
        "data": {
          "name": "label_10_level",
          "text": {
            "fixedValue": "Level 5 (x)"
          },
          "color": {
            "value": -12829636,
            "falpha": 0.0
          },
          "x": 159,
          "y": 80,
          "locked": false
        }
      },
      {
        "type": "label",
        "data": {
          "name": "label_ghost_axe",
          "text": {
            "fixedValue": "Damage Aura"
          },
          "color": {
            "value": -12829636,
            "falpha": 0.0
          },
          "x": 159,
          "y": 89,
          "locked": false
        }
      },
      {
        "type": "image",
        "data": {
          "image": "experience_bottle.png",
          "use1Xscale": false,
          "x": 141,
          "y": 107,
          "locked": false
        }
      },
      {
        "type": "label",
        "data": {
          "name": "label_40_level",
          "text": {
            "fixedValue": "Level 10 (Passive)"
          },
          "color": {
            "value": -12829636,
            "falpha": 0.0
          },
          "x": 159,
          "y": 107,
          "locked": false
        }
      },
      {
        "type": "label",
        "data": {
          "name": "label_survival_instinct",
          "text": {
            "fixedValue": "Bards Speed"
          },
          "color": {
            "value": -12829636,
            "falpha": 0.0
          },
          "x": 159,
          "y": 116,
          "locked": false
        }
      },
      {
        "type": "image",
        "data": {
          "image": "experience_bottle.png",
          "use1Xscale": false,
          "x": 141,
          "y": 134,
          "locked": false
        }
      },
      {
        "type": "label",
        "data": {
          "name": "label_level_60",
          "text": {
            "fixedValue": "Level 15 (c)"
          },
          "color": {
            "value": -12829636,
            "falpha": 0.0
          },
          "x": 159,
          "y": 134,
          "locked": false
        }
      },
      {
        "type": "label",
        "data": {
          "name": "label_invincibility",
          "text": {
            "fixedValue": "Bard Agility !!WIP!!"
          },
          "color": {
            "value": -12829636,
            "falpha": 0.0
          },
          "x": 159,
          "y": 143,
          "locked": false
        }
      },
      {
        "type": "image",
        "data": {
          "image": "experience_bottle.png",
          "use1Xscale": false,
          "x": 141,
          "y": 161,
          "locked": false
        }
      },
      {
        "type": "label",
        "data": {
          "name": "label_level_80_passive",
          "text": {
            "fixedValue": "Level 20 (Passive)"
          },
          "color": {
            "value": -12829636,
            "falpha": 0.0
          },
          "x": 159,
          "y": 161,
          "locked": false
        }
      },
      {
        "type": "label",
        "data": {
          "name": "label_barbarian_strenght",
          "text": {
            "fixedValue": "Better Healing"
          },
          "color": {
            "value": -12829636,
            "falpha": 0.0
          },
          "x": 159,
          "y": 170,
          "locked": false
        }
      },
      {
        "type": "label",
        "data": {
          "name": "label_barbarian",
          "text": {
            "fixedValue": "Bard"
          },
          "color": {
            "value": -12829636,
            "falpha": 0.0
          },
          "x": 204,
          "y": 35,
          "locked": false
        }
      },
      {
        "type": "button",
        "data": {
          "name": "button_choose",
          "text": "Choose",
          "isUndecorated": false,
          "onClick": {
            "name": "Barde"
          },
          "displayCondition": {
            "name": "Displaybutton"
          },
          "width": 56,
          "height": 20,
          "x": 141,
          "y": 188,
          "locked": false
        }
      },
      {
        "type": "button",
        "data": {
          "name": "button_exit",
          "text": "EXIT",
          "isUndecorated": false,
          "onClick": {
            "name": "Exit"
          },
          "displayCondition": {
            "name": "Displaybutton"
          },
          "width": 46,
          "height": 20,
          "x": 240,
          "y": 188,
          "locked": false
        }
      },
      {
        "type": "tooltip",
        "data": {
          "name": "tooltip_get_regen_3_and_saturation_2_for",
          "text": {
            "fixedValue": "Get regen 3 and saturation 2 for 2 seconds"
          },
          "width": 24,
          "height": 24,
          "x": 159,
          "y": 53,
          "locked": false
        }
      },
      {
        "type": "tooltip",
        "data": {
          "name": "tooltip_get_regen_10_instead_of_3_for_5",
          "text": {
            "fixedValue": "Get regen 10 instead of 3 for 5 instead of 2 seconds"
          },
          "width": 24,
          "height": 24,
          "x": 159,
          "y": 161,
          "locked": false
        }
      },
      {
        "type": "tooltip",
        "data": {
          "name": "tooltip_deal_4_hearts_damage_to_every_en",
          "text": {
            "fixedValue": "Deal 4 hearts damage to every entity up to 7.5 blocks away from you"
          },
          "width": 24,
          "height": 24,
          "x": 159,
          "y": 80,
          "locked": false
        }
      },
      {
        "type": "tooltip",
        "data": {
          "name": "tooltip_permanent_speed_and_haste_1",
          "text": {
            "fixedValue": "Permanent speed and haste 1"
          },
          "width": 24,
          "height": 24,
          "x": 159,
          "y": 107,
          "locked": false
        }
      },
      {
        "type": "tooltip",
        "data": {
          "name": "tooltip_remove_your_cooldown_for_10_seco",
          "text": {
            "fixedValue": "Reset your cooldown 5x to 0 every 2 seconds"
          },
          "width": 24,
          "height": 24,
          "x": 159,
          "y": 134,
          "locked": false
        }
      }
    ],
    "gridSettings": {
      "sx": 18,
      "sy": 18,
      "ox": 11,
      "oy": 15,
      "snapOnGrid": true
    }
  }
}